{
  "builders": [
    {
      "boot_command": "",
      "boot_wait": "6m",
      "communicator": "winrm",
      "cpus": 2,
      "disk_size": "{{user `disk_size`}}",
      "floppy_files": [
        "{{user `autounattend`}}",
        "./floppy/WindowsPowershell.lnk",
        "./floppy/PinTo10.exe",
        "./scripts/fixnetwork.ps1",
        "./scripts/disable-screensaver.ps1",
        "./scripts/disable-winrm.ps1",
        "./scripts/enable-winrm.ps1",
        "./scripts/microsoft-updates.bat",
        "./scripts/win-updates.ps1"
      ],
      "guest_additions_mode": "disable",
      "guest_os_type": "Windows10_64",
      "headless": "{{user `headless`}}",
      "iso_checksum": "{{user `iso_checksum`}}",
      "iso_url": "{{user `iso_url`}}",
      "memory": "{{user `memory`}}",
      "shutdown_command": "shutdown /s /t 10 /f /d p:4:1 /c \"Packer Shutdown\"",
      "type": "virtualbox-iso",
      "vm_name": "{{user `vm_name`}}",
      "winrm_password": "vagrant",
      "winrm_timeout": "{{user `winrm_timeout`}}",
      "winrm_username": "vagrant"
    }
  ],
  "provisioners": [
    {
      "execute_command": "{{ .Vars }} cmd /c \"{{ .Path }}\"",
      "remote_path": "/tmp/script.bat",
      "scripts": [
        "./scripts/enable-rdp.bat"
      ],
      "type": "windows-shell"
    },
    {
      "scripts": [
        "./scripts/vm-guest-tools.ps1",
        "./scripts/debloat-windows.ps1"
      ],
      "type": "powershell"
    },
    {
      "restart_timeout": "{{user `restart_timeout`}}",
      "type": "windows-restart"
    },
    {
      "scripts": [
        "./scripts/set-powerplan.ps1",
        "./scripts/docker/disable-windows-defender.ps1"
      ],
      "type": "powershell"
    },
    {
      "execute_command": "{{ .Vars }} cmd /c \"{{ .Path }}\"",
      "remote_path": "/tmp/script.bat",
      "scripts": [
        "./scripts/pin-powershell.bat",
        "./scripts/compile-dotnet-assemblies.bat",
        "./scripts/set-winrm-automatic.bat",
        "./scripts/uac-enable.bat",
        "./scripts/dis-updates.bat",
        "./scripts/compact.bat"
      ],
      "type": "windows-shell"
    }
  ],
  "variables": {
    "autounattend": "",
    "disk_size": "61440",
    "disk_type_id": "1",
    "memory": "2048",
    "headless": "false",
    "iso_checksum": "sha256:7F6538F0EB33C30F0A5CBBF2F39973D4C8DEA0D64F69BD18E406012F17A8234F",
    "iso_url": "./Win10_21H2_English_x64.iso",
    "restart_timeout": "5m",
    "vhv_enable": "false",
    "vm_name": "windows_10",
    "winrm_timeout": "6h"
  }
}
